thunar_plugins/.gitignore
thunar_plugins/__init__.py
thunar_plugins/__main__.py
thunar_plugins/config.py
thunar_plugins/l10n.py
thunar_plugins/log.py
thunar_plugins/thunar-plugins.py
thunar_plugins/version.py
thunar_plugins/locale/.gitignore
thunar_plugins/locale/Makefile
thunar_plugins/locale/de.po
thunar_plugins/locale/de/LC_MESSAGES/thunar-plugins.mo
thunar_plugins/menus/__init__.py
thunar_plugins/menus/git_annex.py
thunar_plugins/menus/hash.py
thunar_plugins/menus/link.py
thunar_plugins/preferences/__init__.py
thunar_plugins/preferences/plugins.py
thunar_plugins/ui/__init__.py
thunar_plugins/ui/git-annex-properties.glade
thunar_plugins/ui/hash.glade
thunar_plugins/ui/plugin-preferences.glade
thunar_plugins-1.4.0.data/data/share/thunarx-python/extensions/thunar-plugins.py
thunar_plugins-1.4.0.dist-info/LICENSE
thunar_plugins-1.4.0.dist-info/METADATA
thunar_plugins-1.4.0.dist-info/WHEEL
thunar_plugins-1.4.0.dist-info/entry_points.txt
thunar_plugins-1.4.0.dist-info/top_level.txt
thunar_plugins-1.4.0.dist-info/RECORD
