Metadata-Version: 2.1
Name: thunar-plugins
Version: 1.4.0
Summary: Plugins for the Thunar file browser
Home-page: https://gitlab.com/nobodyinperson/thunar-plugins
Author: Yann Buechau
Author-email: nobodyinperson@posteo.de
License: GPLv3
Keywords: thunar,plugin
Classifier: License :: OSI Approved :: GNU General Public License v3 (GPLv3)
License-File: LICENSE
Requires-Dist: PyGObject
Requires-Dist: rich
